README.md
setup.py
easyepub/__init__.py
easyepub/easyepub.py
easyepub/utils.py
easyepub.egg-info/PKG-INFO
easyepub.egg-info/SOURCES.txt
easyepub.egg-info/dependency_links.txt
easyepub.egg-info/requires.txt
easyepub.egg-info/top_level.txt
easyepub/models/__init__.py
easyepub/models/book.py