Metadata-Version: 2.1
Name: easyepub
Version: 0.0.8
Summary: Library for easier translating book pages in png.
Home-page: https://github.com/xcaq/easyepub
Author: xcaq
Author-email: swipduces@yandex.com
License: MIT
Platform: UNKNOWN
Classifier: License :: OSI Approved :: MIT License
Classifier: Programming Language :: Python
Classifier: Programming Language :: Python :: 3
Classifier: Programming Language :: Python :: 3.6
Requires-Python: >=3.6.0
